<?xml version="1.0" encoding="iso-8859-1" ?>

<CustomData>
  <CustomGroups>
    <CustomGroup>
      <name>Scholarship_application</name>
      <title>Scholarship application</title>
      <extends>Case</extends>
      <extends_entity_column_value_option_group>case_type</extends_entity_column_value_option_group>
      <extends_entity_column_value></extends_entity_column_value>
      <style>Inline</style>
      <collapse_display>0</collapse_display>
      <help_pre></help_pre>
      <help_post></help_post>
      <weight>7</weight>
      <is_active>1</is_active>
      <table_name>civicrm_value_scholarship_application_7</table_name>
      <is_multiple>0</is_multiple>
      <collapse_adv_display>0</collapse_adv_display>
      <created_date>2018-06-21 16:00:38</created_date>
      <is_reserved>0</is_reserved>
      <is_public>1</is_public>
    </CustomGroup>
  </CustomGroups>
  <CustomFields>
    <CustomField>
      <name>How_do_you_identify_</name>
      <label>How do you identify?</label>
      <data_type>String</data_type>
      <html_type>Multi-Select</html_type>
      <is_required>0</is_required>
      <is_searchable>1</is_searchable>
      <is_search_range>0</is_search_range>
      <weight>8</weight>
      <is_active>1</is_active>
      <is_view>0</is_view>
      <text_length>255</text_length>
      <note_columns>60</note_columns>
      <note_rows>4</note_rows>
      <column_name>how_do_you_identify__42</column_name>
      <in_selector>0</in_selector>
      <option_group_name>how_do_you_identify__20180621160343</option_group_name>
      <custom_group_name>Scholarship_application</custom_group_name>
    </CustomField>
    <CustomField>
      <name>Pronouns_in_use</name>
      <label>Pronouns in use</label>
      <data_type>String</data_type>
      <html_type>Text</html_type>
      <is_required>0</is_required>
      <is_searchable>0</is_searchable>
      <is_search_range>0</is_search_range>
      <weight>13</weight>
      <is_active>1</is_active>
      <is_view>0</is_view>
      <text_length>255</text_length>
      <note_columns>60</note_columns>
      <note_rows>4</note_rows>
      <column_name>pronouns_in_use_43</column_name>
      <in_selector>0</in_selector>
      <custom_group_name>Scholarship_application</custom_group_name>
    </CustomField>
    <CustomField>
      <name>Race_Ethnicity</name>
      <label>Race / Ethnicity</label>
      <data_type>String</data_type>
      <html_type>Text</html_type>
      <is_required>0</is_required>
      <is_searchable>0</is_searchable>
      <is_search_range>0</is_search_range>
      <weight>16</weight>
      <is_active>1</is_active>
      <is_view>0</is_view>
      <text_length>255</text_length>
      <note_columns>60</note_columns>
      <note_rows>4</note_rows>
      <column_name>race_ethnicity_44</column_name>
      <in_selector>0</in_selector>
      <custom_group_name>Scholarship_application</custom_group_name>
    </CustomField>
    <CustomField>
      <name>Religion_Belief</name>
      <label>Religion / Belief</label>
      <data_type>String</data_type>
      <html_type>Text</html_type>
      <is_required>0</is_required>
      <is_searchable>0</is_searchable>
      <is_search_range>0</is_search_range>
      <weight>19</weight>
      <is_active>1</is_active>
      <is_view>0</is_view>
      <text_length>255</text_length>
      <note_columns>60</note_columns>
      <note_rows>4</note_rows>
      <column_name>religion_belief_45</column_name>
      <in_selector>0</in_selector>
      <custom_group_name>Scholarship_application</custom_group_name>
    </CustomField>
    <CustomField>
      <name>Do_you_consider_yourself_to_have_a_disability_</name>
      <label>Do you consider yourself to have a disability?</label>
      <data_type>Boolean</data_type>
      <html_type>Radio</html_type>
      <is_required>0</is_required>
      <is_searchable>1</is_searchable>
      <is_search_range>0</is_search_range>
      <weight>21</weight>
      <is_active>1</is_active>
      <is_view>0</is_view>
      <text_length>255</text_length>
      <note_columns>60</note_columns>
      <note_rows>4</note_rows>
      <column_name>do_you_consider_yourself_to_have_46</column_name>
      <in_selector>0</in_selector>
      <custom_group_name>Scholarship_application</custom_group_name>
    </CustomField>
    <CustomField>
      <name>Do_you_belong_to_any_other_under_represented_group_or_oppressed_</name>
      <label>Do you belong to any other under-represented group or oppressed group in your country/region? Please specify</label>
      <data_type>Boolean</data_type>
      <html_type>Radio</html_type>
      <is_required>0</is_required>
      <is_searchable>0</is_searchable>
      <is_search_range>0</is_search_range>
      <weight>23</weight>
      <is_active>1</is_active>
      <is_view>0</is_view>
      <text_length>255</text_length>
      <note_columns>60</note_columns>
      <note_rows>4</note_rows>
      <column_name>do_you_belong_to_any_other_under_47</column_name>
      <in_selector>0</in_selector>
      <custom_group_name>Scholarship_application</custom_group_name>
    </CustomField>
    <CustomField>
      <name>Have_you_ever_taken_part_in_an_ILGA_World_Conference_or_in_an_IL</name>
      <label>Have you ever taken part in an ILGA World Conference or in an ILGA regional conference before?</label>
      <data_type>Boolean</data_type>
      <html_type>Radio</html_type>
      <is_required>0</is_required>
      <is_searchable>1</is_searchable>
      <is_search_range>0</is_search_range>
      <weight>27</weight>
      <is_active>1</is_active>
      <is_view>0</is_view>
      <text_length>255</text_length>
      <note_columns>60</note_columns>
      <note_rows>4</note_rows>
      <column_name>have_you_ever_taken_part_in_an_i_48</column_name>
      <in_selector>0</in_selector>
      <custom_group_name>Scholarship_application</custom_group_name>
    </CustomField>
    <CustomField>
      <name>If_yes_when_</name>
      <label>If yes, when?</label>
      <data_type>String</data_type>
      <html_type>Text</html_type>
      <is_required>0</is_required>
      <is_searchable>0</is_searchable>
      <is_search_range>0</is_search_range>
      <weight>29</weight>
      <is_active>1</is_active>
      <is_view>0</is_view>
      <text_length>255</text_length>
      <note_columns>60</note_columns>
      <note_rows>4</note_rows>
      <column_name>if_yes_when__49</column_name>
      <in_selector>0</in_selector>
      <custom_group_name>Scholarship_application</custom_group_name>
    </CustomField>
    <CustomField>
      <name>How_would_you_and_your_organisation_benefit_from_your_participat</name>
      <label>How would you and your organisation benefit from your participation to the 2016 ILGA World Conference?</label>
      <data_type>Memo</data_type>
      <html_type>TextArea</html_type>
      <is_required>0</is_required>
      <is_searchable>0</is_searchable>
      <is_search_range>0</is_search_range>
      <weight>31</weight>
      <attributes>rows=4, cols=60</attributes>
      <is_active>1</is_active>
      <is_view>0</is_view>
      <note_columns>60</note_columns>
      <note_rows>4</note_rows>
      <column_name>how_would_you_and_your_organisat_50</column_name>
      <in_selector>0</in_selector>
      <custom_group_name>Scholarship_application</custom_group_name>
    </CustomField>
    <CustomField>
      <name>How_would_your_participation_contribute_to_the_mission_and_work_</name>
      <label>How would your participation contribute to the mission and work of ILGA?</label>
      <data_type>Memo</data_type>
      <html_type>TextArea</html_type>
      <is_required>0</is_required>
      <is_searchable>0</is_searchable>
      <is_search_range>0</is_search_range>
      <weight>33</weight>
      <attributes>rows=4, cols=60</attributes>
      <is_active>1</is_active>
      <is_view>0</is_view>
      <note_columns>60</note_columns>
      <note_rows>4</note_rows>
      <column_name>how_would_your_participation_con_51</column_name>
      <in_selector>0</in_selector>
      <custom_group_name>Scholarship_application</custom_group_name>
    </CustomField>
    <CustomField>
      <name>Are_you_interested_in_</name>
      <label>Are you interested in:</label>
      <data_type>String</data_type>
      <html_type>Multi-Select</html_type>
      <is_required>0</is_required>
      <is_searchable>0</is_searchable>
      <is_search_range>0</is_search_range>
      <weight>35</weight>
      <is_active>1</is_active>
      <is_view>0</is_view>
      <text_length>255</text_length>
      <note_columns>60</note_columns>
      <note_rows>4</note_rows>
      <column_name>are_you_interested_in__52</column_name>
      <in_selector>0</in_selector>
      <option_group_name>are_you_interested_in__20180618193327</option_group_name>
      <custom_group_name>Scholarship_application</custom_group_name>
    </CustomField>
    <CustomField>
      <name>Please_specify_about_the_under_representation</name>
      <label>Please specify about the under-representation</label>
      <data_type>Memo</data_type>
      <html_type>TextArea</html_type>
      <is_required>0</is_required>
      <is_searchable>0</is_searchable>
      <is_search_range>0</is_search_range>
      <weight>25</weight>
      <attributes>rows=4, cols=60</attributes>
      <is_active>1</is_active>
      <is_view>0</is_view>
      <note_columns>60</note_columns>
      <note_rows>4</note_rows>
      <column_name>please_specify_about_the_under_r_53</column_name>
      <in_selector>0</in_selector>
      <custom_group_name>Scholarship_application</custom_group_name>
    </CustomField>
    <CustomField>
      <name>There_will_probably_be_a_two_to_three_day_meeting_to_discuss_glo</name>
      <label>There will [probably] be a two to three day meeting to discuss global LGBTI strategies at the United Nations on approximately 26 to 28 November 2016. Is this a meeting that you would be interested in attending?</label>
      <data_type>Boolean</data_type>
      <html_type>Radio</html_type>
      <is_required>0</is_required>
      <is_searchable>0</is_searchable>
      <is_search_range>0</is_search_range>
      <weight>37</weight>
      <is_active>1</is_active>
      <is_view>0</is_view>
      <text_length>255</text_length>
      <note_columns>60</note_columns>
      <note_rows>4</note_rows>
      <column_name>there_will_probably_be_a_two_to__54</column_name>
      <in_selector>0</in_selector>
      <custom_group_name>Scholarship_application</custom_group_name>
    </CustomField>
    <CustomField>
      <name>If_so_please_provide_details_of_your_experience_or_interest_in_p</name>
      <label>If so, please provide details of your experience or interest in promoting LGBTI issues by using the United Nations systems.</label>
      <data_type>Memo</data_type>
      <html_type>TextArea</html_type>
      <is_required>0</is_required>
      <is_searchable>0</is_searchable>
      <is_search_range>0</is_search_range>
      <weight>39</weight>
      <attributes>rows=4, cols=60</attributes>
      <is_active>1</is_active>
      <is_view>0</is_view>
      <note_columns>60</note_columns>
      <note_rows>4</note_rows>
      <column_name>if_so_please_provide_details_of__55</column_name>
      <in_selector>0</in_selector>
      <custom_group_name>Scholarship_application</custom_group_name>
    </CustomField>
    <CustomField>
      <name>Are_you_applying_for_a_full_or_a_partial_scholarship_</name>
      <label>Are you applying for a full or a partial scholarship?</label>
      <data_type>String</data_type>
      <html_type>Radio</html_type>
      <is_required>0</is_required>
      <is_searchable>1</is_searchable>
      <is_search_range>0</is_search_range>
      <weight>41</weight>
      <is_active>1</is_active>
      <is_view>0</is_view>
      <text_length>255</text_length>
      <note_columns>60</note_columns>
      <note_rows>4</note_rows>
      <column_name>are_you_applying_for_a_full_or_a_56</column_name>
      <in_selector>0</in_selector>
      <option_group_name>are_you_applying_for_a_full_or_a_20180621170108</option_group_name>
      <custom_group_name>Scholarship_application</custom_group_name>
    </CustomField>
    <CustomField>
      <name>If_you_are_applying_for_a_partial_scholarship_how_much_funding_a</name>
      <label>If you are applying for a partial scholarship, how much funding are you able to obtain from other sources?</label>
      <data_type>Memo</data_type>
      <html_type>TextArea</html_type>
      <is_required>0</is_required>
      <is_searchable>0</is_searchable>
      <is_search_range>0</is_search_range>
      <weight>43</weight>
      <attributes>rows=4, cols=60</attributes>
      <is_active>1</is_active>
      <is_view>0</is_view>
      <note_columns>60</note_columns>
      <note_rows>4</note_rows>
      <column_name>if_you_are_applying_for_a_partia_57</column_name>
      <in_selector>0</in_selector>
      <custom_group_name>Scholarship_application</custom_group_name>
    </CustomField>
    <CustomField>
      <name>Please_describe_any_other_issue_ILGA_should_consider_in_awarding</name>
      <label>Please describe any other issue ILGA should consider in awarding you a scholarship.</label>
      <data_type>Memo</data_type>
      <html_type>TextArea</html_type>
      <is_required>0</is_required>
      <is_searchable>0</is_searchable>
      <is_search_range>0</is_search_range>
      <weight>45</weight>
      <attributes>rows=4, cols=60</attributes>
      <is_active>1</is_active>
      <is_view>0</is_view>
      <note_columns>60</note_columns>
      <note_rows>4</note_rows>
      <column_name>please_describe_any_other_issue__58</column_name>
      <in_selector>0</in_selector>
      <custom_group_name>Scholarship_application</custom_group_name>
    </CustomField>
    <CustomField>
      <name>Please_describe_your_motivation_for_wanting_to_take_part_in_ILGA</name>
      <label>Please describe your motivation for wanting to take part in ILGA's World Conference 2019</label>
      <data_type>Memo</data_type>
      <html_type>TextArea</html_type>
      <is_required>0</is_required>
      <is_searchable>0</is_searchable>
      <is_search_range>0</is_search_range>
      <weight>47</weight>
      <attributes>rows=4, cols=60</attributes>
      <is_active>1</is_active>
      <is_view>0</is_view>
      <note_columns>60</note_columns>
      <note_rows>4</note_rows>
      <column_name>please_describe_your_motivation__59</column_name>
      <in_selector>0</in_selector>
      <custom_group_name>Scholarship_application</custom_group_name>
    </CustomField>
    <CustomField>
      <name>Activity_in_organisation</name>
      <label>Activity in organisation</label>
      <data_type>Memo</data_type>
      <html_type>TextArea</html_type>
      <is_required>0</is_required>
      <is_searchable>0</is_searchable>
      <is_search_range>0</is_search_range>
      <weight>7</weight>
      <attributes>rows=4, cols=60</attributes>
      <is_active>1</is_active>
      <is_view>0</is_view>
      <note_columns>60</note_columns>
      <note_rows>4</note_rows>
      <column_name>activity_in_organisation_60</column_name>
      <in_selector>0</in_selector>
      <custom_group_name>Scholarship_application</custom_group_name>
    </CustomField>
    <CustomField>
      <name>Score</name>
      <label>Score</label>
      <data_type>Float</data_type>
      <html_type>Text</html_type>
      <default_value>0</default_value>
      <is_required>0</is_required>
      <is_searchable>0</is_searchable>
      <is_search_range>0</is_search_range>
      <weight>48</weight>
      <is_active>1</is_active>
      <is_view>1</is_view>
      <text_length>255</text_length>
      <note_columns>60</note_columns>
      <note_rows>4</note_rows>
      <column_name>score_61</column_name>
      <in_selector>0</in_selector>
      <custom_group_name>Scholarship_application</custom_group_name>
    </CustomField>
    <CustomField>
      <name>Score_Explanation</name>
      <label>Score Explanation</label>
      <data_type>Memo</data_type>
      <html_type>TextArea</html_type>
      <is_required>0</is_required>
      <is_searchable>0</is_searchable>
      <is_search_range>0</is_search_range>
      <weight>49</weight>
      <attributes>rows=4, cols=60</attributes>
      <is_active>1</is_active>
      <is_view>0</is_view>
      <note_columns>60</note_columns>
      <note_rows>4</note_rows>
      <column_name>score_explanation_62</column_name>
      <in_selector>0</in_selector>
      <custom_group_name>Scholarship_application</custom_group_name>
    </CustomField>
  </CustomFields>
  <OptionGroups>
    <OptionGroup>
      <name>how_do_you_identify__20180621160343</name>
      <title>How do you identify?</title>
      <data_type>String</data_type>
      <is_reserved>1</is_reserved>
      <is_active>1</is_active>
    </OptionGroup>
    <OptionGroup>
      <name>are_you_interested_in__20180618193327</name>
      <title>Are you interested in:</title>
      <data_type>String</data_type>
      <is_reserved>1</is_reserved>
      <is_active>1</is_active>
    </OptionGroup>
    <OptionGroup>
      <name>are_you_applying_for_a_full_or_a_20180621170108</name>
      <title>Are you applying for a full or a partial scholarship?</title>
      <data_type>String</data_type>
      <is_reserved>1</is_reserved>
      <is_active>1</is_active>
    </OptionGroup>
  </OptionGroups>
  <OptionValues>
    <OptionValue>
      <label>Lesbian</label>
      <value>1</value>
      <name>Lesbian</name>
      <is_default>0</is_default>
      <weight>1</weight>
      <is_optgroup>0</is_optgroup>
      <is_reserved>0</is_reserved>
      <is_active>1</is_active>
      <option_group_name>how_do_you_identify__20180621160343</option_group_name>
    </OptionValue>
    <OptionValue>
      <label>Gay</label>
      <value>2</value>
      <name>Gay</name>
      <is_default>0</is_default>
      <weight>2</weight>
      <is_optgroup>0</is_optgroup>
      <is_reserved>0</is_reserved>
      <is_active>1</is_active>
      <option_group_name>how_do_you_identify__20180621160343</option_group_name>
    </OptionValue>
    <OptionValue>
      <label>Bisexual</label>
      <value>3</value>
      <name>Bisexual</name>
      <is_default>0</is_default>
      <weight>3</weight>
      <is_optgroup>0</is_optgroup>
      <is_reserved>0</is_reserved>
      <is_active>1</is_active>
      <option_group_name>how_do_you_identify__20180621160343</option_group_name>
    </OptionValue>
    <OptionValue>
      <label>Trans</label>
      <value>4</value>
      <name>Trans</name>
      <is_default>0</is_default>
      <weight>4</weight>
      <is_optgroup>0</is_optgroup>
      <is_reserved>0</is_reserved>
      <is_active>1</is_active>
      <option_group_name>how_do_you_identify__20180621160343</option_group_name>
    </OptionValue>
    <OptionValue>
      <label>Intersex</label>
      <value>5</value>
      <name>Intersex</name>
      <is_default>0</is_default>
      <weight>5</weight>
      <is_optgroup>0</is_optgroup>
      <is_reserved>0</is_reserved>
      <is_active>1</is_active>
      <option_group_name>how_do_you_identify__20180621160343</option_group_name>
    </OptionValue>
    <OptionValue>
      <label>Queer</label>
      <value>6</value>
      <name>Queer</name>
      <is_default>0</is_default>
      <weight>6</weight>
      <is_optgroup>0</is_optgroup>
      <is_reserved>0</is_reserved>
      <is_active>1</is_active>
      <option_group_name>how_do_you_identify__20180621160343</option_group_name>
    </OptionValue>
    <OptionValue>
      <label>Cis man</label>
      <value>7</value>
      <name>Cis_man</name>
      <is_default>0</is_default>
      <weight>7</weight>
      <is_optgroup>0</is_optgroup>
      <is_reserved>0</is_reserved>
      <is_active>1</is_active>
      <option_group_name>how_do_you_identify__20180621160343</option_group_name>
    </OptionValue>
    <OptionValue>
      <label>Cis woman</label>
      <value>8</value>
      <name>Cis_woman</name>
      <is_default>0</is_default>
      <weight>8</weight>
      <is_optgroup>0</is_optgroup>
      <is_reserved>0</is_reserved>
      <is_active>1</is_active>
      <option_group_name>how_do_you_identify__20180621160343</option_group_name>
    </OptionValue>
    <OptionValue>
      <label>Non-binary</label>
      <value>9</value>
      <name>Non_binary</name>
      <is_default>0</is_default>
      <weight>9</weight>
      <is_optgroup>0</is_optgroup>
      <is_reserved>0</is_reserved>
      <is_active>1</is_active>
      <option_group_name>how_do_you_identify__20180621160343</option_group_name>
    </OptionValue>
    <OptionValue>
      <label>Genderqueer</label>
      <value>10</value>
      <name>Genderqueer</name>
      <is_default>0</is_default>
      <weight>10</weight>
      <is_optgroup>0</is_optgroup>
      <is_reserved>0</is_reserved>
      <is_active>1</is_active>
      <option_group_name>how_do_you_identify__20180621160343</option_group_name>
    </OptionValue>
    <OptionValue>
      <label>UN advocacy</label>
      <value>1</value>
      <name>UN_advocacy</name>
      <is_default>0</is_default>
      <weight>1</weight>
      <is_optgroup>0</is_optgroup>
      <is_reserved>0</is_reserved>
      <is_active>1</is_active>
      <option_group_name>are_you_interested_in__20180618193327</option_group_name>
    </OptionValue>
    <OptionValue>
      <label>Interfaith work</label>
      <value>2</value>
      <name>Interfaith_work</name>
      <is_default>0</is_default>
      <weight>2</weight>
      <is_optgroup>0</is_optgroup>
      <is_reserved>0</is_reserved>
      <is_active>1</is_active>
      <option_group_name>are_you_interested_in__20180618193327</option_group_name>
    </OptionValue>
    <OptionValue>
      <label>Trans issues</label>
      <value>3</value>
      <name>Trans_issues</name>
      <is_default>0</is_default>
      <weight>3</weight>
      <is_optgroup>0</is_optgroup>
      <is_reserved>0</is_reserved>
      <is_active>1</is_active>
      <option_group_name>are_you_interested_in__20180618193327</option_group_name>
    </OptionValue>
    <OptionValue>
      <label>Intersex issues</label>
      <value>4</value>
      <name>Intersex_issues</name>
      <is_default>0</is_default>
      <weight>4</weight>
      <is_optgroup>0</is_optgroup>
      <is_reserved>0</is_reserved>
      <is_active>1</is_active>
      <option_group_name>are_you_interested_in__20180618193327</option_group_name>
    </OptionValue>
    <OptionValue>
      <label>Women&rsquo;s issues</label>
      <value>5</value>
      <name>Women_s_issues</name>
      <is_default>0</is_default>
      <weight>5</weight>
      <is_optgroup>0</is_optgroup>
      <is_reserved>0</is_reserved>
      <is_active>1</is_active>
      <option_group_name>are_you_interested_in__20180618193327</option_group_name>
    </OptionValue>
    <OptionValue>
      <label>Bisexual issues</label>
      <value>6</value>
      <name>Bisexual_issues</name>
      <is_default>0</is_default>
      <weight>6</weight>
      <is_optgroup>0</is_optgroup>
      <is_reserved>0</is_reserved>
      <is_active>1</is_active>
      <option_group_name>are_you_interested_in__20180618193327</option_group_name>
    </OptionValue>
    <OptionValue>
      <label>LGBTI Health issues</label>
      <value>7</value>
      <name>LGBTI_Health_issues</name>
      <is_default>0</is_default>
      <weight>7</weight>
      <is_optgroup>0</is_optgroup>
      <is_reserved>0</is_reserved>
      <is_active>1</is_active>
      <option_group_name>are_you_interested_in__20180618193327</option_group_name>
    </OptionValue>
    <OptionValue>
      <label>Education</label>
      <value>8</value>
      <name>Education</name>
      <is_default>0</is_default>
      <weight>8</weight>
      <is_optgroup>0</is_optgroup>
      <is_reserved>0</is_reserved>
      <is_active>1</is_active>
      <option_group_name>are_you_interested_in__20180618193327</option_group_name>
    </OptionValue>
    <OptionValue>
      <label>Other</label>
      <value>9</value>
      <name>Other</name>
      <is_default>0</is_default>
      <weight>9</weight>
      <is_optgroup>0</is_optgroup>
      <is_reserved>0</is_reserved>
      <is_active>1</is_active>
      <option_group_name>are_you_interested_in__20180618193327</option_group_name>
    </OptionValue>
    <OptionValue>
      <label>Full</label>
      <value>1</value>
      <name>Full</name>
      <is_default>0</is_default>
      <weight>1</weight>
      <is_optgroup>0</is_optgroup>
      <is_reserved>0</is_reserved>
      <is_active>1</is_active>
      <option_group_name>are_you_applying_for_a_full_or_a_20180621170108</option_group_name>
    </OptionValue>
    <OptionValue>
      <label>Partial</label>
      <value>2</value>
      <name>Partial</name>
      <is_default>0</is_default>
      <weight>2</weight>
      <is_optgroup>0</is_optgroup>
      <is_reserved>0</is_reserved>
      <is_active>1</is_active>
      <option_group_name>are_you_applying_for_a_full_or_a_20180621170108</option_group_name>
    </OptionValue>
  </OptionValues>
</CustomData>
